cached_modelforms/__init__.py
cached_modelforms/fields.py
cached_modelforms/forms.py
cached_modelforms/models.py
django_cached_modelforms-0.2.3.dist-info/LICENSE
django_cached_modelforms-0.2.3.dist-info/METADATA
django_cached_modelforms-0.2.3.dist-info/WHEEL
django_cached_modelforms-0.2.3.dist-info/top_level.txt
django_cached_modelforms-0.2.3.dist-info/RECORD
