Metadata-Version: 2.1
Name: django-cached-modelforms
Version: 0.2.3
Summary: ModelChoiceField implementation that can accept lists of objects, not just querysets
Home-page: https://github.com/drtyrsa/django-cached-modelforms
Author: Vlad Starostin
Author-email: drtyrsa@yandex.ru
License: BSD License
Download-URL: https://github.com/drtyrsa/django-cached-modelforms/zipball/master
Platform: UNKNOWN
Classifier: Development Status :: 4 - Beta
Classifier: Framework :: Django
Classifier: Intended Audience :: Developers
Classifier: License :: OSI Approved :: BSD License
Classifier: Natural Language :: English
Classifier: Operating System :: OS Independent
Classifier: Programming Language :: Python
Classifier: Programming Language :: Python :: 2
Classifier: Programming Language :: Python :: 2.6
Classifier: Programming Language :: Python :: 3
Classifier: Programming Language :: Python :: 3.3
Classifier: Topic :: Internet :: WWW/HTTP
Classifier: Topic :: Software Development :: Libraries :: Python Modules
Requires: Django (>=1.4)
Requires-Dist: six
